src/main/python/sphyrna/service_manager/__init__.py
src/main/python/sphyrna/service_manager/service.py
src/main/python/sphyrna/service_manager/service_configuration.py
src/main/python/sphyrna/service_manager/service_instance_provider.py
src/main/python/sphyrna/service_manager/service_lifecycle_controller.py
src/main/python/sphyrna/service_manager/service_manager.py
src/main/python/sphyrna/service_manager/service_manager_strategy.py
sphyrna_service_manager-0.3.7.dist-info/METADATA
sphyrna_service_manager-0.3.7.dist-info/WHEEL
sphyrna_service_manager-0.3.7.dist-info/RECORD
